hypothesis_sqlalchemy/__init__.py
hypothesis_sqlalchemy/hints.py
hypothesis_sqlalchemy/py.typed
hypothesis_sqlalchemy/sample.py
hypothesis_sqlalchemy/scheme.py
hypothesis_sqlalchemy/core/__init__.py
hypothesis_sqlalchemy/core/column.py
hypothesis_sqlalchemy/core/column_type.py
hypothesis_sqlalchemy/core/columns_records.py
hypothesis_sqlalchemy/core/enum.py
hypothesis_sqlalchemy/core/hints.py
hypothesis_sqlalchemy/core/table.py
hypothesis_sqlalchemy/core/table_constraints.py
hypothesis_sqlalchemy/core/table_records.py
hypothesis_sqlalchemy/core/utils.py
hypothesis_sqlalchemy-1.1.0.dist-info/LICENSE
hypothesis_sqlalchemy-1.1.0.dist-info/METADATA
hypothesis_sqlalchemy-1.1.0.dist-info/WHEEL
hypothesis_sqlalchemy-1.1.0.dist-info/top_level.txt
hypothesis_sqlalchemy-1.1.0.dist-info/RECORD
