Metadata-Version: 2.1
Name: hypothesis-sqlalchemy
Version: 1.1.0
Summary: ``hypothesis`` strategies for ``SQLAlchemy`` objects and data from them.
Home-page: https://github.com/lycantropos/hypothesis_sqlalchemy/
Download-URL: https://github.com/lycantropos/hypothesis_sqlalchemy/archive/master.zip
Author: Azat Ibrakov
Author-email: azatibrakov@gmail.com
License: MIT License
Keywords: SQLAlchemy,hypothesis
Classifier: Development Status :: 3 - Alpha
Classifier: Environment :: Web Environment
Classifier: Framework :: Hypothesis
Classifier: Intended Audience :: Developers
Classifier: License :: OSI Approved :: MIT License
Classifier: Programming Language :: Python :: 3.7
Classifier: Programming Language :: Python :: 3.8
Classifier: Programming Language :: Python :: 3.9
Classifier: Programming Language :: Python :: 3.10
Classifier: Programming Language :: Python :: 3.11
Classifier: Programming Language :: Python :: Implementation :: CPython
Classifier: Programming Language :: Python :: Implementation :: PyPy
Classifier: Operating System :: POSIX
Classifier: Operating System :: MacOS :: MacOS X
Classifier: Operating System :: Microsoft :: Windows
Classifier: Topic :: Database :: Database Engines/Servers
Requires-Python: >=3.7
License-File: LICENSE
Requires-Dist: sqlalchemy (<3.0,>=1.4.46)
Requires-Dist: hypothesis (<7.0,>=6.66.0)
